{
  "metadata": {
    "total_urls": 36,
    "last_audit": "2026-03-27",
    "audit_method": "manual_verification + automated_http_spot_check"
  },
  "urls": [
    {
      "url": "https://doi.org/10.1088/0264-9381/11/5/001",
      "source_id": "src-001",
      "status": "reachable",
      "last_checked": "2026-03-21",
      "notes": "IOP Publishing — stable DOI"
    },
    {
      "url": "https://arxiv.org/abs/gr-qc/9702026",
      "source_id": "src-002",
      "status": "reachable",
      "last_checked": "2026-03-21",
      "notes": "arXiv — stable preprint archive"
    },
    {
      "url": "https://doi.org/10.1088/1361-6382/abe692",
      "source_id": "src-004",
      "status": "reachable",
      "last_checked": "2026-03-21",
      "notes": "IOP Publishing — stable DOI"
    },
    {
      "url": "https://doi.org/10.1103/PhysRevD.105.064038",
      "source_id": "src-005",
      "status": "access_restricted",
      "last_checked": "2026-03-21",
      "notes": "APS — stable DOI"
    },
    {
      "url": "https://doi.org/10.1088/1361-6382/abdf6e",
      "source_id": "src-006",
      "status": "reachable",
      "last_checked": "2026-03-21",
      "notes": "IOP Publishing — stable DOI"
    },
    {
      "url": "https://doi.org/10.1098/rsta.1920.0009",
      "source_id": "src-010",
      "status": "access_restricted",
      "last_checked": "2026-03-21",
      "notes": "Royal Society — stable DOI, historical"
    },
    {
      "url": "https://doi.org/10.1038/nature10561",
      "source_id": "src-016",
      "status": "reachable",
      "last_checked": "2026-03-21",
      "notes": "Nature — stable DOI"
    },
    {
      "url": "https://doi.org/10.1007/BF02345020",
      "source_id": "src-019",
      "status": "reachable",
      "last_checked": "2026-03-21",
      "notes": "Springer — stable DOI"
    },
    {
      "url": "https://doi.org/10.1103/PhysRevLett.85.3966",
      "source_id": "src-025",
      "status": "access_restricted",
      "last_checked": "2026-03-21",
      "notes": "APS — stable DOI"
    },
    {
      "url": "https://arxiv.org/abs/1306.0533",
      "source_id": "src-009",
      "status": "reachable",
      "last_checked": "2026-03-21",
      "notes": "arXiv — stable preprint archive"
    },
    {
      "url": "https://www.dni.gov/files/ODNI/documents/assessments/Prelimary-Assessment-UAP-20210625.pdf",
      "source_id": "src-031",
      "status": "reachable",
      "last_checked": "2026-03-21",
      "notes": "ODNI — US Government official document. Note: filename contains typo 'Prelimary' in original URL"
    },
    {
      "url": "https://www.dni.gov/files/ODNI/documents/assessments/Unclassified-2022-Annual-Report-UAP.pdf",
      "source_id": "src-032",
      "status": "reachable",
      "last_checked": "2026-03-21",
      "notes": "ODNI — US Government official document"
    },
    {
      "url": "https://media.defense.gov/2024/Mar/08/2003409233/-1/-1/0/DOPSR-2024-0175-HISTORICAL-RECORD-REPORT-VOLUME-I-2024.PDF",
      "source_id": "src-033",
      "status": "access_restricted",
      "last_checked": "2026-03-21",
      "notes": "DoD — AARO Historical Record Report"
    },
    {
      "url": "https://www.aaro.mil/Portals/136/PDFs/Information%20Papers/ORNL-Synopsis_Analysis_of_a_Metallic_Specimen.pdf",
      "source_id": "src-034",
      "status": "access_restricted",
      "last_checked": "2026-03-22",
      "notes": "AARO/ORNL direct PDF — metallic specimen synopsis; currently returns HTTP 403 to scripted requests"
    },
    {
      "url": "https://www.dni.gov/files/documents/ICD/ICD-203.pdf",
      "source_id": "src-035",
      "status": "reachable",
      "last_checked": "2026-03-21",
      "notes": "ODNI — Intelligence Community Directive, updated official document path"
    },
    {
      "url": "https://irp.fas.org/dia/aatip-list.pdf",
      "source_id": "dird-index",
      "status": "reachable",
      "last_checked": "2026-03-21",
      "notes": "FAS — DIRD master list (declassified)"
    },
    {
      "url": "https://documents2.theblackvault.com/documents/dia/AAWSAP-DIRDs/",
      "source_id": "dird-collection",
      "status": "reachable",
      "last_checked": "2026-03-21",
      "notes": "The Black Vault — FOIA-released DIRD collection"
    },
    {
      "url": "https://www.llnl.gov/news/national-ignition-facility-achieves-fusion-ignition",
      "source_id": "nif-ignition",
      "status": "reachable",
      "last_checked": "2026-03-21",
      "notes": "LLNL — NIF ignition announcement Dec 2022"
    },
    {
      "url": "https://lasers.llnl.gov/about/what-is-nif",
      "source_id": "nif-about",
      "status": "reachable",
      "last_checked": "2026-03-21",
      "notes": "LLNL — NIF technical overview"
    },
    {
      "url": "https://www.iter.org/",
      "source_id": "iter",
      "status": "reachable",
      "last_checked": "2026-03-21",
      "notes": "ITER — International fusion project official site"
    },
    {
      "url": "https://www.cfs.energy/",
      "source_id": "cfs-sparc",
      "status": "reachable",
      "last_checked": "2026-03-21",
      "notes": "Commonwealth Fusion Systems — SPARC project"
    },
    {
      "url": "https://arxiv.org/abs/1110.6064",
      "source_id": "src-053",
      "status": "reachable",
      "last_checked": "2026-03-21",
      "notes": "arXiv — stable preprint archive"
    },
    {
      "url": "https://ntrs.nasa.gov/",
      "source_id": "nasa-ntrs",
      "status": "reachable",
      "last_checked": "2026-03-21",
      "notes": "NASA Technical Reports Server — acceleration and thermal data"
    },
    {
      "url": "https://www.congress.gov/bill/117th-congress/senate-bill/3600",
      "source_id": "ndaa-2023",
      "status": "access_restricted",
      "last_checked": "2026-03-21",
      "notes": "Congress.gov — NDAA 2023 with UAP provisions; currently returns HTTP 403 to scripted requests"
    },
    {
      "url": "https://oversight.house.gov/hearing/unidentified-anomalous-phenomena-implications-on-national-security-public-safety-and-government-transparency/",
      "source_id": "house-uap-hearing-2023",
      "status": "reachable",
      "last_checked": "2026-03-21",
      "notes": "House Oversight Committee — July 2023 UAP hearing"
    },
    {
      "url": "https://www.nytimes.com/2017/12/16/us/politics/pentagon-program-ufo-harry-reid.html",
      "source_id": "nyt-aatip-2017",
      "status": "access_restricted",
      "last_checked": "2026-03-21",
      "notes": "NYT — original AATIP disclosure (may require subscription)"
    },
    {
      "url": "https://doi.org/10.1103/PhysRevLett.116.061102",
      "source_id": "src-012",
      "status": "access_restricted",
      "last_checked": "2026-03-21",
      "notes": "APS — LIGO gravitational wave detection"
    },
    {
      "url": "https://doi.org/10.1103/PhysRevLett.129.121102",
      "source_id": "src-013",
      "status": "access_restricted",
      "last_checked": "2026-03-21",
      "notes": "APS — MICROSCOPE equivalence principle test"
    },
    {
      "url": "https://documents2.theblackvault.com/documents/dia/AAWSAP-DIRDs/AAWSAP-DIRDs-1-37.zip",
      "source_id": "dird-zip-archive",
      "status": "reachable",
      "last_checked": "2026-03-21",
      "notes": "The Black Vault — ZIP archive backup for the FOIA-released DIRD collection"
    },
    {
      "url": "https://doi.org/10.3390/e21100939",
      "source_id": "src-055",
      "status": "access_restricted",
      "last_checked": "2026-03-22",
      "notes": "MDPI — Knuth et al. (2019) UAP flight characteristics estimation; currently returns HTTP 403 to scripted requests"
    },
    {
      "url": "https://science.nasa.gov/uap/",
      "source_id": "src-056",
      "status": "reachable",
      "last_checked": "2026-03-21",
      "notes": "NASA — UAP Independent Study Team report page"
    },
    {
      "url": "https://webarchive.nationalarchives.gov.uk/ukgwa/20121110115327/http://www.mod.uk/DefenceInternet/FreedomOfInformation/PublicationScheme/SearchPublicationScheme/UnidentifiedAerialPhenomenauapInTheUkAirDefenceRegion.htm",
      "source_id": "src-057",
      "status": "reachable",
      "last_checked": "2026-03-22",
      "notes": "UK National Archives web archive — preserved copy of the MOD Project Condign publication page"
    },
    {
      "url": "https://www.aaro.mil/Portals/136/PDFs/Information%20Papers/AARO_Effect_of_Forced_Perspective_and_Parallax_View_on_UAP_Observations_2024.pdf",
      "source_id": "src-058",
      "status": "access_restricted",
      "last_checked": "2026-03-22",
      "notes": "AARO direct PDF — parallax and forced perspective paper; currently returns HTTP 403 to scripted requests"
    },
    {
      "url": "https://lasers.llnl.gov/science/achieving-fusion-ignition",
      "source_id": "src-059",
      "status": "reachable",
      "last_checked": "2026-03-21",
      "notes": "LLNL — NIF ignition achievements page including April 2025 records"
    },
    {
      "url": "https://doi.org/10.1037/0021-843X.111.3.455",
      "source_id": "src-060",
      "status": "access_restricted",
      "last_checked": "2026-03-27",
      "notes": "APA DOI — Clancy et al. (2002) memory distortion paper; currently returns HTTP 403 to scripted requests"
    },
    {
      "url": "https://doi.org/10.1006/ccog.1999.0404",
      "source_id": "src-061",
      "status": "reachable",
      "last_checked": "2026-03-27",
      "notes": "Academic Press DOI — Cheyne et al. (1999) sleep-paralysis hallucination paper"
    }
  ]
}
